vexdb/psycopg2/__init__.py
vexdb/psycopg2/floatvector.py
vexdb/psycopg2/register.py
vexdb/sqlalchemy/__init__.py
vexdb/sqlalchemy/floatvector.py
vexdb/sqlalchemy/functions.py
vexdb/utils/__init__.py
vexdb/utils/vector.py
pyvector_vexdb-1.0.2.dist-info/METADATA
pyvector_vexdb-1.0.2.dist-info/WHEEL
pyvector_vexdb-1.0.2.dist-info/top_level.txt
pyvector_vexdb-1.0.2.dist-info/RECORD
