Metadata-Version: 2.4
Name: pyvector-vexdb
Version: 1.0.2
Summary: pyvector support for vexdb
Author-email: vexdb <contact@vexdb.io>
License: MIT
Project-URL: Homepage, http://vexdb.siftdb.com/
Requires-Python: >=3.8
Requires-Dist: numpy
